cpsm/__init__.py
cpsm/cpsm.py
cpsm/templates/cpsm_config_template.j2
cpsm-1.1.2.data/scripts/cpsm
cpsm-1.1.2.dist-info/LICENSE
cpsm-1.1.2.dist-info/METADATA
cpsm-1.1.2.dist-info/WHEEL
cpsm-1.1.2.dist-info/top_level.txt
cpsm-1.1.2.dist-info/RECORD
