Metadata-Version: 2.1
Name: cpsm
Version: 1.1.2
Summary: Competitive Programming Solutions Manager
Home-page: http://github.com/btjanaka/cpsm
Author: Bryon Tjanaka
Author-email: bryon.tjanaka@gmail.com
License: MIT
Keywords: competitive-programming solutions kattis leetcode hackerrank uva
Platform: UNKNOWN
Classifier: License :: OSI Approved :: MIT License
Classifier: Programming Language :: Python :: 3
Classifier: Programming Language :: Python :: 3.6
Requires-Dist: Jinja2 (>=2.10.1)
